[
	{
		"path": ["userpanel", "sms", "sent"],
		"controller": "controllers\\sms@sent",
		"method":"get"
	},
	{
		"path": ["userpanel", "sms", "get"],
		"controller": "controllers\\sms@get",
		"method":"get"
	},
	{
		"path": ["userpanel", "sms", "send"],
		"controller": "controllers\\sms@send",
		"method":["get","post"]
	},
	{
		"path":["userpanel","settings","sms","gateways"],
		"controller": "controllers\\settings\\gateways@listgateways",
		"method":"get"
	},
	{
		"path":["userpanel","settings","sms","gateways","add"],
		"controller": "controllers\\settings\\gateways@add",
		"method":["get","post"]
	},
	{
		"path":["userpanel","settings","sms","gateways","delete",{"type":"dynamic","name":"gateway", "regex":"/^\\d+$/"}],
		"controller": "controllers\\settings\\gateways@delete",
		"method":["get","post"]
	},
	{
		"path":["userpanel","settings","sms","gateways","edit",{"type":"dynamic","name":"gateway", "regex":"/^\\d+$/"}],
		"controller": "controllers\\settings\\gateways@edit",
		"method":["get","post"]
	}
]
